<?xml version="1.0" encoding="UTF-8"?><!DOCTYPE mapper PUBLIC "-//mybatis.org//DTD Mapper 3.0//EN" "http://mybatis.org/dtd/mybatis-3-mapper.dtd"><!-- create by AutoCode,v1.0.0 --><mapper namespace="com.zhoubi.graindepot.mapper.ProvinceMapper">	<insert id="insert" parameterType="com.zhoubi.graindepot.bean.Province" useGeneratedKeys="true" keyProperty="provinceid">		insert into l_province		(		provincecode		,provincename		,orderno		,longitude		,latitude		)		values		(		#{provincecode}		,#{provincename}		,#{orderno}		,#{longitude}		,#{latitude}	)</insert>	<insert id="insertList" parameterType="java.util.List" useGeneratedKeys="true" >		insert into l_province		(		provincecode		,provincename		,orderno		,longitude		,latitude		)		values		<foreach collection="list" item="item" index="index" separator=",">		 (		#{item.provincecode}		,#{item.provincename}		,#{item.orderno}		,#{item.longitude}		,#{item.latitude}	) </foreach></insert>	<update id="update" parameterType="com.zhoubi.graindepot.bean.Province">		update l_province		  set provinceid=provinceid		,provincecode=#{provincecode}		,provincename=#{provincename}		,orderno=#{orderno}		,longitude=#{longitude}		,latitude=#{latitude}		 where provinceid=#{provinceid}	</update>	<update id="updateMap" parameterType="Map">		update l_province		  set provinceid=provinceid 		<if test="provincecode != null"> ,provincecode=#{provincecode} </if>		<if test="provincename != null"> ,provincename=#{provincename} </if>		<if test="orderno != null"> ,orderno=#{orderno} </if>		<if test="longitude != null"> ,longitude=#{longitude} </if>		<if test="latitude != null"> ,latitude=#{latitude} </if>		 where 1=1 		<if test="Where_IdsStr != null"> and provinceid in (${Where_IdsStr}) </if>		<if test="Where_Id != null"> and provinceid =#{Where_Id} </if>		<if test="Where_provinceid != null"> and provinceid=#{Where_provinceid} </if>		<if test="Where_provincecode != null"> and provincecode=#{Where_provincecode} </if>		<if test="Where_provincename != null"> and provincename=#{Where_provincename} </if>		<if test="Where_orderno != null"> and orderno=#{Where_orderno} </if>		<if test="Where_longitude != null"> and longitude=#{Where_longitude} </if>		<if test="Where_latitude != null"> and latitude=#{Where_latitude} </if>	</update>	<select id="selectById" parameterType="int" resultType="com.zhoubi.graindepot.bean.Province">	 select 		t.provinceid "provinceid",		t.provincecode "provincecode",		t.provincename "provincename",		t.orderno "orderno",		t.longitude "longitude",		t.latitude "latitude"	 from l_province t where provinceid=#{provinceid}	</select>	<select id="selectOne" parameterType="Map" resultType="com.zhoubi.graindepot.bean.Province">	 select 		t.provinceid "provinceid",		t.provincecode "provincecode",		t.provincename "provincename",		t.orderno "orderno",		t.longitude "longitude",		t.latitude "latitude"	 from l_province t where 1=1 		 <if test="provinceid != null"> and t.provinceid=#{provinceid} </if>		 <if test="provincecode != null"> and t.provincecode=#{provincecode} </if>		 <if test="provincename != null"> and t.provincename=#{provincename} </if>		 <if test="orderno != null"> and t.orderno=#{orderno} </if>		 <if test="longitude != null"> and t.longitude=#{longitude} </if>		 <if test="latitude != null"> and t.latitude=#{latitude} </if>	</select>	<select id="selectList" parameterType="Map" resultType="com.zhoubi.graindepot.bean.Province">	 select 		t.provinceid "provinceid",		t.provincecode "provincecode",		t.provincename "provincename",		t.orderno "orderno",		t.longitude "longitude",		t.latitude "latitude"	 from l_province t where 1=1 		 <if test="provinceid != null"> and t.provinceid=#{provinceid} </if>		 <if test="provincecode != null"> and t.provincecode=#{provincecode} </if>		 <if test="provincename != null"> and t.provincename=#{provincename} </if>		 <if test="orderno != null"> and t.orderno=#{orderno} </if>		 <if test="longitude != null"> and t.longitude=#{longitude} </if>		 <if test="latitude != null"> and t.latitude=#{latitude} </if>	</select>	<delete id="deleteMap" parameterType="Map">		delete from l_province where 1=1 		<if test="Where_IdsStr != null"> and provinceid in (${Where_IdsStr}) </if>		<if test="Where_Id != null"> and provinceid =#{Where_Id} </if>		<if test="Where_provinceid != null"> and provinceid=#{Where_provinceid} </if>		<if test="Where_provincecode != null"> and provincecode=#{Where_provincecode} </if>		<if test="Where_provincename != null"> and provincename=#{Where_provincename} </if>		<if test="Where_orderno != null"> and orderno=#{Where_orderno} </if>		<if test="Where_longitude != null"> and longitude=#{Where_longitude} </if>		<if test="Where_latitude != null"> and latitude=#{Where_latitude} </if>	</delete>	<sql id="page_template">		<if test="orders != null">		 order by 		<foreach collection="orders" item="order" separator=",">		 ${order} 		</foreach>		</if>		 limit #{offset},#{pageSize} 	</sql> 	<select id="selectPageList" parameterType="Map" resultType="com.zhoubi.graindepot.bean.Province">	 select 		t.provinceid "provinceid",		t.provincecode "provincecode",		t.provincename "provincename",		t.orderno "orderno",		t.longitude "longitude",		t.latitude "latitude"	 from l_province t where 1=1 		<if test="provinceid!=null "> and t.provinceid=#{provinceid} </if>		<if test="provincecode!=null "> and t.provincecode=#{provincecode} </if>		<if test="provincename!=null "> and t.provincename=#{provincename} </if>		<if test="orderno!=null "> and t.orderno=#{orderno} </if>		<if test="longitude!=null "> and t.longitude=#{longitude} </if>		<if test="latitude!=null "> and t.latitude=#{latitude} </if>		 <include refid="page_template"/> 	</select> 	<select id="selectPageCount" parameterType="Map" resultType="int">	 select count(*) from l_province t where 1=1 		<if test="provinceid!=null "> and t.provinceid=#{provinceid} </if>		<if test="NoId!=null "> and t.provinceid!=#{NoId} </if>		<if test="provincecode!=null "> and t.provincecode=#{provincecode} </if>		<if test="provincename!=null "> and t.provincename=#{provincename} </if>		<if test="orderno!=null "> and t.orderno=#{orderno} </if>		<if test="longitude!=null "> and t.longitude=#{longitude} </if>		<if test="latitude!=null "> and t.latitude=#{latitude} </if>	</select> </mapper>