<?xml version="1.0" encoding="UTF-8"?><!DOCTYPE mapper PUBLIC "-//mybatis.org//DTD Mapper 3.0//EN" "http://mybatis.org/dtd/mybatis-3-mapper.dtd"><!-- create by AutoCode,v1.0.0 --><mapper namespace="com.zhoubi.graindepot.mapper.StoragestructureMapper">	<insert id="insert" parameterType="com.zhoubi.graindepot.bean.Storagestructure" useGeneratedKeys="true" keyProperty="storageStructureID">		insert into l_storagestructure		(		storagestructurename		,orderno		)		values		(		#{storagestructurename}		,#{orderno}	)</insert>	<insert id="insertList" parameterType="java.util.List" useGeneratedKeys="true" >		insert into l_storagestructure		(		storagestructurename		,orderno		)		values		<foreach collection="list" item="item" index="index" separator=",">		 (		#{item.storagestructurename}		,#{item.orderno}	) </foreach></insert>	<update id="update" parameterType="com.zhoubi.graindepot.bean.Storagestructure">		update l_storagestructure		  set storagestructureid=storagestructureid		,storagestructurename=#{storagestructurename}		,orderno=#{orderno}		 where storagestructureid=#{storagestructureid}	</update>	<update id="updateMap" parameterType="Map">		update l_storagestructure		  set storagestructureid=storagestructureid		<if test="storagestructurename != null"> ,storagestructurename=#{storagestructurename} </if>		<if test="orderno != null"> ,orderno=#{orderno} </if>		 where 1=1 		<if test="Where_IdsStr != null"> and storageStructureID in (${Where_IdsStr}) </if>		<if test="Where_Id != null"> and storageStructureID =#{Where_Id} </if>		<if test="where_storagestructureid != null"> and storagestructureid=#{where_storagestructureid} </if>		<if test="where_storagestructurename != null"> and storagestructurename=#{where_storagestructurename} </if>		<if test="Where_orderno != null"> and orderno=#{Where_orderno} </if>	</update>	<select id="selectById" parameterType="int" resultType="com.zhoubi.graindepot.bean.Storagestructure">	 select 		t.storagestructureid "storagestructureid",		t.storagestructurename "storagestructurename",		t.orderno "orderno"	 from l_storagestructure t where storagestructureid=#{storagestructureid}	</select>	<select id="selectOne" parameterType="Map" resultType="com.zhoubi.graindepot.bean.Storagestructure">	 select 		t.storagestructureid "storagestructureid",		t.storagestructurename "storagestructurename",		t.orderno "orderno"	 from l_storagestructure t where 1=1 		 <if test="storagestructureid != null"> and t.storagestructureid=#{storagestructureid} </if>		 <if test="storagestructurename != null"> and t.storagestructurename=#{storagestructurename} </if>		 <if test="orderno != null"> and t.orderno=#{orderno} </if>	</select>	<select id="selectList" parameterType="Map" resultType="com.zhoubi.graindepot.bean.Storagestructure">	 select 		t.storagestructureid "storagestructureid",		t.storagestructurename "storagestructurename",		t.orderno "orderno"	 from l_storagestructure t where 1=1 		 <if test="storagestructureid != null"> and t.storagestructureid=#{storagestructureid} </if>		 <if test="storagestructurename != null"> and t.storagestructurename=#{storagestructurename} </if>		 <if test="orderno != null"> and t.orderno=#{orderno} </if>	</select>	<delete id="deleteMap" parameterType="Map">		delete from l_storagestructure where 1=1		<if test="Where_IdsStr != null"> and storagestructureid in (${Where_IdsStr}) </if>		<if test="Where_Id != null"> and storagestructureid =#{Where_Id} </if>		<if test="Where_storagestructureid != null"> and storagestructureid=#{Where_storagestructureid} </if>		<if test="Where_storagestructurename != null"> and storagestructurename=#{Where_storagestructurename} </if>		<if test="Where_orderno != null"> and orderno=#{Where_orderno} </if>	</delete>	<sql id="page_template">		<if test="orders != null">		 order by 		<foreach collection="orders" item="order" separator=",">		 ${order} 		</foreach>		</if>		 limit #{offset},#{pageSize} 	</sql> 	<select id="selectPageList" parameterType="Map" resultType="com.zhoubi.graindepot.bean.Storagestructure">	 select 		t.storagestructureid "storagestructureid",		t.storagestructurename "storagestructurename",		t.orderno "orderno"	 from l_storagestructure t where 1=1 		<if test="storagestructureid!=null "> and t.storagestructureid=#{storagestructureid} </if>		<if test="storagestructurename!=null "> and t.storagestructurename=#{storagestructurename} </if>		<if test="orderno!=null "> and t.orderno=#{orderno} </if>		 <include refid="page_template"/> 	</select> 	<select id="selectPageCount" parameterType="Map" resultType="int">	 select count(*) from l_storagestructure t where 1=1 		<if test="storagestructureid!=null "> and t.storagestructureid=#{storagestructureid} </if>		<if test="NoId!=null "> and t.storagestructureid!=#{NoId} </if>		<if test="storagestructurename!=null "> and t.storagestructurename=#{storagestructurename} </if>		<if test="orderno!=null "> and t.orderno=#{orderno} </if>	</select> </mapper>